odoo/addons/ssi_hr_overtime/README.rst
odoo/addons/ssi_hr_overtime/__init__.py
odoo/addons/ssi_hr_overtime/__manifest__.py
odoo/addons/ssi_hr_overtime/data/approval_template_data.xml
odoo/addons/ssi_hr_overtime/data/ir_sequence_data.xml
odoo/addons/ssi_hr_overtime/data/policy_template_data.xml
odoo/addons/ssi_hr_overtime/data/sequence_template_data.xml
odoo/addons/ssi_hr_overtime/demo/hr_overtime_type_data_demo.xml
odoo/addons/ssi_hr_overtime/models/__init__.py
odoo/addons/ssi_hr_overtime/models/hr_overtime.py
odoo/addons/ssi_hr_overtime/models/hr_overtime_type.py
odoo/addons/ssi_hr_overtime/models/hr_timesheet.py
odoo/addons/ssi_hr_overtime/models/hr_timesheet_attendance.py
odoo/addons/ssi_hr_overtime/security/ir.model.access.csv
odoo/addons/ssi_hr_overtime/security/ir_module_category_data.xml
odoo/addons/ssi_hr_overtime/security/ir_rule_data.xml
odoo/addons/ssi_hr_overtime/security/res_group_data.xml
odoo/addons/ssi_hr_overtime/static/description/icon.png
odoo/addons/ssi_hr_overtime/views/hr_overtime_type_views.xml
odoo/addons/ssi_hr_overtime/views/hr_overtime_views.xml
odoo/addons/ssi_hr_overtime/views/hr_timesheet_views.xml
odoo14_addon_ssi_hr_overtime-14.0.1.5.0.dist-info/METADATA
odoo14_addon_ssi_hr_overtime-14.0.1.5.0.dist-info/WHEEL
odoo14_addon_ssi_hr_overtime-14.0.1.5.0.dist-info/top_level.txt
odoo14_addon_ssi_hr_overtime-14.0.1.5.0.dist-info/RECORD
